airflow_fxiaoke/__init__.py
airflow_fxiaoke/provider.yaml
airflow_fxiaoke/hooks/__init__.py
airflow_fxiaoke/hooks/query.py
airflow_fxiaoke/operators/__init__.py
airflow_fxiaoke/operators/fxiaoke_to_gcs.py
airflow_provider_fxiaoke-0.0.9.dist-info/LICENSE
airflow_provider_fxiaoke-0.0.9.dist-info/METADATA
airflow_provider_fxiaoke-0.0.9.dist-info/WHEEL
airflow_provider_fxiaoke-0.0.9.dist-info/entry_points.txt
airflow_provider_fxiaoke-0.0.9.dist-info/top_level.txt
airflow_provider_fxiaoke-0.0.9.dist-info/RECORD
